kapusta/__init__.py
kapusta/core.py
kapusta/crud.py
kapusta/models.py
kapusta/types.py
kapusta-0.1.3.dist-info/LICENSE
kapusta-0.1.3.dist-info/METADATA
kapusta-0.1.3.dist-info/WHEEL
kapusta-0.1.3.dist-info/RECORD
