Metadata-Version: 2.1
Name: kapusta
Version: 0.1.3
Summary: A simple asynchronous task manager using sqlalchemy as a broker and result backend
Home-page: https://github.com/EliseyGodX/Kapusta
License: MIT
Author: EliseyGodX
Requires-Python: >=3.12,<4.0
Classifier: License :: OSI Approved :: MIT License
Classifier: Programming Language :: Python :: 3
Classifier: Programming Language :: Python :: 3.12
Classifier: Programming Language :: Python :: 3.13
Requires-Dist: asyncpg (>=0.30.0,<0.31.0)
Requires-Dist: sqlalchemy (>=2.0.38,<3.0.0)
Project-URL: Repository, https://github.com/EliseyGodX/Kapusta
